djangocms_bootstrap5/__init__.py
djangocms_bootstrap5/constants.py
djangocms_bootstrap5/fields.py
djangocms_bootstrap5/helpers.py
djangocms_bootstrap5/contrib/__init__.py
djangocms_bootstrap5/contrib/bootstrap5_alerts/__init__.py
djangocms_bootstrap5/contrib/bootstrap5_alerts/cms_plugins.py
djangocms_bootstrap5/contrib/bootstrap5_alerts/models.py
djangocms_bootstrap5/contrib/bootstrap5_alerts/migrations/0001_initial.py
djangocms_bootstrap5/contrib/bootstrap5_alerts/migrations/__init__.py
djangocms_bootstrap5/contrib/bootstrap5_alerts/templates/djangocms_bootstrap5/alerts.html
djangocms_bootstrap5/contrib/bootstrap5_alerts/templates/djangocms_bootstrap5/admin/alerts.html
djangocms_bootstrap5/contrib/bootstrap5_badge/__init__.py
djangocms_bootstrap5/contrib/bootstrap5_badge/cms_plugins.py
djangocms_bootstrap5/contrib/bootstrap5_badge/models.py
djangocms_bootstrap5/contrib/bootstrap5_badge/migrations/0001_initial.py
djangocms_bootstrap5/contrib/bootstrap5_badge/migrations/__init__.py
djangocms_bootstrap5/contrib/bootstrap5_badge/templates/djangocms_bootstrap5/badge.html
djangocms_bootstrap5/contrib/bootstrap5_badge/templates/djangocms_bootstrap5/admin/badge.html
djangocms_bootstrap5/contrib/bootstrap5_card/__init__.py
djangocms_bootstrap5/contrib/bootstrap5_card/cms_plugins.py
djangocms_bootstrap5/contrib/bootstrap5_card/constants.py
djangocms_bootstrap5/contrib/bootstrap5_card/models.py
djangocms_bootstrap5/contrib/bootstrap5_card/migrations/0001_initial.py
djangocms_bootstrap5/contrib/bootstrap5_card/migrations/__init__.py
djangocms_bootstrap5/contrib/bootstrap5_card/templates/djangocms_bootstrap5/card.html
djangocms_bootstrap5/contrib/bootstrap5_card/templates/djangocms_bootstrap5/card_content.html
djangocms_bootstrap5/contrib/bootstrap5_card/templates/djangocms_bootstrap5/admin/card.html
djangocms_bootstrap5/contrib/bootstrap5_carousel/__init__.py
djangocms_bootstrap5/contrib/bootstrap5_carousel/cms_plugins.py
djangocms_bootstrap5-0.1.0.dist-info/LICENSE
djangocms_bootstrap5-0.1.0.dist-info/METADATA
djangocms_bootstrap5-0.1.0.dist-info/WHEEL
djangocms_bootstrap5-0.1.0.dist-info/top_level.txt
djangocms_bootstrap5-0.1.0.dist-info/RECORD
