Metadata-Version: 2.1
Name: djangocms-bootstrap5
Version: 0.1.0
Summary: Adds Bootstrap 5 components as plugins.
Home-page: https://github.com/divio/djangocms-bootstrap5
Author: Divio AG
Author-email: info@divio.ch
License: BSD-3-Clause
Platform: UNKNOWN
Classifier: Development Status :: 2 - Pre-Alpha
Classifier: Environment :: Web Environment
Classifier: Intended Audience :: Developers
Classifier: License :: OSI Approved :: BSD License
Classifier: Operating System :: OS Independent
Classifier: Programming Language :: Python
Classifier: Programming Language :: Python :: 3
Classifier: Programming Language :: Python :: 3.5
Classifier: Programming Language :: Python :: 3.6
Classifier: Programming Language :: Python :: 3.7
Classifier: Programming Language :: Python :: 3.8
Classifier: Framework :: Django
Classifier: Framework :: Django :: 2.2
Classifier: Framework :: Django :: 3.0
Classifier: Framework :: Django :: 3.1
Classifier: Framework :: Django CMS
Classifier: Framework :: Django CMS :: 3.7
Classifier: Framework :: Django CMS :: 3.8
Classifier: Topic :: Internet :: WWW/HTTP
Classifier: Topic :: Internet :: WWW/HTTP :: Dynamic Content
Classifier: Topic :: Software Development
Classifier: Topic :: Software Development :: Libraries
License-File: LICENSE
Requires-Dist: django-cms (>=3.7)
Requires-Dist: django-filer (>=1.7)
Requires-Dist: djangocms-attributes-field (>=1)
Requires-Dist: djangocms-text-ckeditor (>=3.1.0)
Requires-Dist: djangocms-icon (>=1.4.0)
Requires-Dist: djangocms-link (>=2.5.0)
Requires-Dist: djangocms-picture (>=2.3.0)
